[
    {
        "status":  "Sold",
        "id":  "test-id-1",
        "notes":  "Test record",
        "discount":  10,
        "paymentMode":  "UPI/GPay",
        "sareeFabric":  "Banarasi Silk",
        "sareeCode":  "AIMIT-B01",
        "customerPhone":  "9988776655",
        "price":  8500,
        "qty":  1,
        "totalAmount":  7650,
        "customerName":  "Priya Sharma",
        "dateTime":  "2026-07-15T14:00:00.000Z"
    },
    {
        "status":  "Sold",
        "id":  "test-id-2",
        "notes":  "Special packaging requested",
        "discount":  5,
        "paymentMode":  "Cash",
        "sareeFabric":  "Kanjeevaram Silk",
        "sareeCode":  "AIMIT-K02",
        "customerPhone":  "9876543210",
        "price":  12500,
        "qty":  1,
        "totalAmount":  11875,
        "customerName":  "Ananya Sen",
        "dateTime":  "2026-07-15T15:30:00.000Z"
    }
]
